value/__init__.py
value/client.py
value/instrumentation.py
value/internal/__init__.py
value/internal/_api.py
value/internal/actions.py
value/internal/config.py
value/internal/span_processor.py
value/internal/tracing.py
value_python-0.1.6.dist-info/METADATA
value_python-0.1.6.dist-info/WHEEL
value_python-0.1.6.dist-info/licenses/LICENSE
value_python-0.1.6.dist-info/RECORD
