Metadata-Version: 2.4
Name: value-python
Version: 0.1.6
Summary: Python SDK to track AI agents with Value actions and auto-instrument LLM calls (Gemini, LangChain)
License: MIT
License-File: LICENSE
Keywords: opentelemetry,observability,tracing,ai,agents,genai,llm
Author: srinivas
Author-email: srinivas@valmi.io
Requires-Python: >=3.9,<3.14
Classifier: Development Status :: 4 - Beta
Classifier: Intended Audience :: Developers
Classifier: License :: OSI Approved :: MIT License
Classifier: Programming Language :: Python :: 3
Classifier: Programming Language :: Python :: 3.9
Classifier: Programming Language :: Python :: 3.10
Classifier: Programming Language :: Python :: 3.11
Classifier: Programming Language :: Python :: 3.12
Classifier: Programming Language :: Python :: 3.13
Classifier: Topic :: Software Development :: Libraries :: Python Modules
Classifier: Topic :: System :: Monitoring
Classifier: Typing :: Typed
Provides-Extra: all
Provides-Extra: genai
Provides-Extra: langchain
Requires-Dist: google-genai (>=0.1.0) ; extra == "genai" or extra == "all"
Requires-Dist: httpx (>=0.24.0)
Requires-Dist: opentelemetry-api (>=1.20.0)
Requires-Dist: opentelemetry-exporter-otlp-proto-grpc (>=1.20.0)
Requires-Dist: opentelemetry-instrumentation (>=0.41b0)
Requires-Dist: opentelemetry-instrumentation-google-generativeai (>=0.47.0) ; extra == "genai" or extra == "all"
Requires-Dist: opentelemetry-instrumentation-langchain (>=0.47.0) ; extra == "langchain" or extra == "all"
Requires-Dist: opentelemetry-sdk (>=1.20.0)
Project-URL: Documentation, https://github.com/valmi-io/value-python#readme
Project-URL: Homepage, https://github.com/valmi-io/value-python
Project-URL: Issues, https://github.com/valmi-io/value-python/issues
Project-URL: Repository, https://github.com/valmi-io/value-python
